DjPyForms/__init__.py
DjPyForms/django_integration.py
DjPyForms/form_generator.py
DjPyForms/utils.py
DjPyForms/management/__init__.py
DjPyForms/management/commands/__init__.py
DjPyForms/management/commands/createform.py
DjPyForms-0.1.2.dist-info/LICENSE
DjPyForms-0.1.2.dist-info/METADATA
DjPyForms-0.1.2.dist-info/WHEEL
DjPyForms-0.1.2.dist-info/entry_points.txt
DjPyForms-0.1.2.dist-info/top_level.txt
DjPyForms-0.1.2.dist-info/RECORD
