Metadata-Version: 2.1
Name: DjPyForms
Version: 0.1.2
Summary: A tool for automatic Django form generation
Home-page: https://github.com/Charl12-gb/pyform.git
Author: Charles GBOYOU
Author-email: gboyoucharles22@gmail.com
Classifier: Development Status :: 3 - Alpha
Classifier: Intended Audience :: Developers
Classifier: Framework :: Django
Classifier: License :: OSI Approved :: MIT License
Classifier: Programming Language :: Python :: 3
Classifier: Programming Language :: Python :: 3.7
Classifier: Programming Language :: Python :: 3.8
Classifier: Programming Language :: Python :: 3.9
Classifier: Operating System :: OS Independent
Requires-Python: >=3.7
License-File: LICENSE
Requires-Dist: Django >=3.2
